testflo/__init__.py
testflo/__main__.py
testflo/benchmark.py
testflo/cover.py
testflo/deprecations.py
testflo/devnull.py
testflo/discover.py
testflo/duration.py
testflo/filters.py
testflo/isolatedrun.py
testflo/main.py
testflo/mpirun.py
testflo/options.py
testflo/printer.py
testflo/qman.py
testflo/runner.py
testflo/summary.py
testflo/test.py
testflo/util.py
testflo/utresult.py
testflo/tests/__init__.py
testflo/tests/test_nested_fixtures.py
testflo/tests/test_testflo.py
testflo-1.4.20.dist-info/METADATA
testflo-1.4.20.dist-info/WHEEL
testflo-1.4.20.dist-info/entry_points.txt
testflo-1.4.20.dist-info/licenses/LICENSE.txt
testflo-1.4.20.dist-info/RECORD
